MANIFEST.in
README.rst
classifiers.txt
requirements-dev.txt
requirements.txt
setup.py
version.txt
rdc/__init__.py
rdc.etl.egg-info/PKG-INFO
rdc.etl.egg-info/SOURCES.txt
rdc.etl.egg-info/dependency_links.txt
rdc.etl.egg-info/entry_points.txt
rdc.etl.egg-info/namespace_packages.txt
rdc.etl.egg-info/requires.txt
rdc.etl.egg-info/top_level.txt
rdc/etl/__init__.py
rdc/etl/error.py
rdc/etl/hash.py
rdc/etl/job.py
rdc/etl/stat.py
rdc/etl/util.py
rdc/etl/extra/__init__.py
rdc/etl/extra/example.py
rdc/etl/extra/simple.py
rdc/etl/extra/unittest.py
rdc/etl/extra/util.py
rdc/etl/extra/db/__init__.py
rdc/etl/extra/db/extract.py
rdc/etl/extra/db/join.py
rdc/etl/extra/db/load.py
rdc/etl/extra/db/misc.py
rdc/etl/extra/db/sql.py
rdc/etl/extra/filemanager/__init__.py
rdc/etl/extra/tools/__init__.py
rdc/etl/extra/tools/template.py
rdc/etl/harness/__init__.py
rdc/etl/harness/base.py
rdc/etl/harness/threaded.py
rdc/etl/io/__init__.py
rdc/etl/status/__init__.py
rdc/etl/status/console.py
rdc/etl/status/http.py
rdc/etl/test/__init__.py
rdc/etl/test/hash_test.py
rdc/etl/test/io_test.py
rdc/etl/test/transform_extract_test.py
rdc/etl/test/transform_filter_test.py
rdc/etl/test/transform_flow_test.py
rdc/etl/test/transform_map_test.py
rdc/etl/test/transform_map_xml_test.py
rdc/etl/test/transform_simple_test.py
rdc/etl/test/util_test.py
rdc/etl/transform/__init__.py
rdc/etl/transform/util.py
rdc/etl/transform/extract/__init__.py
rdc/etl/transform/extract/file.py
rdc/etl/transform/filter/__init__.py
rdc/etl/transform/flow/__init__.py
rdc/etl/transform/flow/sort.py
rdc/etl/transform/flow/sortedjoin.py
rdc/etl/transform/flow/split.py
rdc/etl/transform/join/__init__.py
rdc/etl/transform/load/__init__.py
rdc/etl/transform/map/__init__.py
rdc/etl/transform/map/csv.py
rdc/etl/transform/map/split.py
rdc/etl/transform/map/xml.py