Metadata-Version: 1.1
Name: rdc.etl
Version: 1.0.0a6
Summary: Extract Transform Load (ETL) toolkit for python
Home-page: http://etl.rdc.li/
Author: Romain Dorgueil
Author-email: romain@dorgueil.net
License: Apache License, Version 2.0
Download-URL: https://github.com/rdcli/rdc.etl/tarball/1.0.0a6
Keywords: ETL Data-Integration
Platform: UNKNOWN
Classifier: Development Status :: 3 - Alpha
Classifier: Environment :: Console
Classifier: Intended Audience :: Information Technology
Classifier: Intended Audience :: System Administrators
Classifier: Intended Audience :: Developers
Classifier: License :: OSI Approved :: Apache Software License
Classifier: Operating System :: OS Independent
Classifier: Natural Language :: English
Classifier: Programming Language :: Python
Classifier: Topic :: Database
Classifier: Topic :: Utilities
Classifier: Topic :: Text Processing :: Filters
